ATCForm/AUTO_FORM.py
ATCForm/AUTO_TASK.py
ATCForm/__init__.py
ATCForm/examlpe.py
ATCForm/utils.py
ATCForm-0.1.9.1.dist-info/LICENSE
ATCForm-0.1.9.1.dist-info/METADATA
ATCForm-0.1.9.1.dist-info/WHEEL
ATCForm-0.1.9.1.dist-info/top_level.txt
ATCForm-0.1.9.1.dist-info/RECORD
